qrandom/__init__.py
qrandom/_api.py
qrandom/_cli.py
qrandom/_generator.py
qrandom/numpy.py
quantum_random-1.4.2.dist-info/METADATA
quantum_random-1.4.2.dist-info/WHEEL
quantum_random-1.4.2.dist-info/entry_points.txt
quantum_random-1.4.2.dist-info/licenses/LICENSE
quantum_random-1.4.2.dist-info/RECORD
