Metadata-Version: 2.3
Name: quantum-random
Version: 1.4.2
Summary: Quantum random numbers
Project-URL: Homepage, https://github.com/sbalian/quantum-random
Project-URL: Repository, https://github.com/sbalian/quantum-random
Author-email: Seto Balian <seto.balian@gmail.com>
Maintainer-email: Seto Balian <seto.balian@gmail.com>
License: MIT License
Keywords: quantum,random,statistics
Classifier: Intended Audience :: Developers
Classifier: Intended Audience :: Science/Research
Classifier: License :: OSI Approved :: MIT License
Classifier: Operating System :: MacOS
Classifier: Operating System :: Microsoft :: Windows
Classifier: Operating System :: Unix
Classifier: Programming Language :: Python
Classifier: Programming Language :: Python :: 3
Classifier: Topic :: Scientific/Engineering
Classifier: Topic :: Software Development
Classifier: Typing :: Typed
Requires-Python: >=3.9
Requires-Dist: click>=8.1.7
Requires-Dist: requests>=2.32.3
Requires-Dist: xdg>=6.0.0
Provides-Extra: numpy
Requires-Dist: numpy>=2.0.2; extra == 'numpy'
Requires-Dist: randomgen>=2.1.1; extra == 'numpy'
